{
  "difficultyRating" : 3.4,
	"LEC": [
		{
      "instructorRating" : 2.4,
			"courseName": "French Culture and Wine",
			"instructor": "Jacqueline Cunningham",
			"id": "FOOD080301",
			"info": {
				"department": "FOOD",
				"courseNumber": "080",
				"sectionNumber": "301"
			},
			"fullfillRequirement": [],
			"preReq": [],
			"time": {
				"start": 14,
				"end": 15,
				"day": "MW"
			}
		}
	],
	"courseName": "French Culture and Wine",
	"courseDescription": "The art and beauty of tasting wine."
}
